lngdetector/__init__.py
lngdetector/detect.py
lngdetector/extension_lang.py
lngdetector/mime_lang.py
lngdetector/report.py
tests/__init__.py
tests/test_detect.py
tests/test_report.py
lngdetector-2025.5.81751.dist-info/METADATA
lngdetector-2025.5.81751.dist-info/WHEEL
lngdetector-2025.5.81751.dist-info/entry_points.txt
lngdetector-2025.5.81751.dist-info/top_level.txt
lngdetector-2025.5.81751.dist-info/RECORD
